myprintx/__init__.py
myprintx/core.py
myprintx-1.0.3.dist-info/licenses/LICENSE
tests/__init__.py
tests/test_myprintx.py
myprintx-1.0.3.dist-info/METADATA
myprintx-1.0.3.dist-info/WHEEL
myprintx-1.0.3.dist-info/top_level.txt
myprintx-1.0.3.dist-info/RECORD
